{
  "sport": "afl",
  "current_season": 2026,
  "ratings": {
    "Sydney": 1747.89,
    "Geelong": 1690.18,
    "Fremantle": 1685.38,
    "Brisbane Lions": 1669.78,
    "Hawthorn": 1618.58,
    "Gold Coast SUNS": 1581.51,
    "St Kilda": 1560.76,
    "Melbourne": 1541.75,
    "Adelaide": 1532.01,
    "Collingwood": 1522.72,
    "Port Adelaide": 1494.3,
    "GWS GIANTS": 1453.36,
    "Western Bulldogs": 1432.65,
    "Carlton": 1406.41,
    "Essendon": 1334.46,
    "West Coast": 1277.05,
    "North Melbourne": 1255.83,
    "Richmond": 1195.36
  }
}