{
  "sport": "mlb",
  "current_season": 2026,
  "ratings": {
    "Los Angeles Dodgers": 1568.53,
    "Milwaukee Brewers": 1549.17,
    "Atlanta Braves": 1541.2,
    "New York Yankees": 1530.8,
    "Philadelphia Phillies": 1526.88,
    "Chicago Cubs": 1526.02,
    "Tampa Bay Rays": 1519.49,
    "Boston Red Sox": 1508.3,
    "Seattle Mariners": 1507.94,
    "Baltimore Orioles": 1507.01,
    "San Diego Padres": 1505.56,
    "Chicago White Sox": 1501.99,
    "Cleveland Guardians": 1501.48,
    "Cleveland Indians": 1498.57,
    "Detroit Tigers": 1496.98,
    "Miami Marlins": 1495.87,
    "Houston Astros": 1495.61,
    "Toronto Blue Jays": 1495.13,
    "St. Louis Cardinals": 1494.75,
    "Texas Rangers": 1493.64,
    "Arizona Diamondbacks": 1491.26,
    "Washington Nationals": 1485.53,
    "Minnesota Twins": 1485.0,
    "Pittsburgh Pirates": 1483.25,
    "Oakland Athletics": 1482.89,
    "Athletics": 1481.32,
    "Cincinnati Reds": 1476.58,
    "New York Mets": 1475.58,
    "Kansas City Royals": 1473.95,
    "San Francisco Giants": 1473.91,
    "Los Angeles Angels": 1468.65,
    "Colorado Rockies": 1457.14
  }
}